{
  "Android": {
    "Overview": [
      "android/overview/android-introduction",
      "android/overview/android-open-source",
      "android/overview/android-changelog"
    ],
    "Quick start": [
      "android/quick-start/android-declare",
      "android/quick-start/android-prepare",
      "android/quick-start/android-init-sdk",
      "android/quick-start/android-create-room",
      "android/quick-start/android-join-room"
    ],
    "Features": [
      "android/guides/android-document",
      "android/guides/android-state",
      "android/guides/android-tools",
      "android/guides/android-view",
      "android/guides/android-operation",
      "android/guides/android-events",
      "android/guides/android-scenes",
      "android/guides/android-replay"
    ],
    "Upgrade": [
      "android/guides/android-v2migration"
    ]
  },
  "iOS": {
    "Overview": [
      "ios/overview/ios-introduction",
      "ios/overview/ios-open-source",
      "ios/overview/ios-changelog"
    ],
    "Quick start": [
      "ios/quick-start/ios-declare",
      "ios/quick-start/ios-prepare",
      "ios/quick-start/ios-init-sdk",
      "ios/quick-start/ios-create-room",
      "ios/quick-start/ios-join-room",
      "ios/quick-start/ios-callback-lifecycle"
    ],
    "Features": [
      "ios/guides/ios-document",
      "ios/guides/ios-state",
      "ios/guides/ios-tools",
      "ios/guides/ios-view",
      "ios/guides/ios-operation",
      "ios/guides/ios-events",
      "ios/guides/ios-scenes",
      "ios/guides/ios-replay"
    ],
    "Upgrade": [
      "ios/guides/ios-v2migration"
    ]
  },
  "JavaScript": {
    "Document structure": [
      "javascript/overview/js-outline"
    ],
    "Installation guide": [
      "javascript/guide/js-sdk",
      "javascript/guide/js-changelog",
      "javascript/guide/js-open-source",
      "javascript/guide/js-debug"
    ],
    "Quick start": [
      "javascript/quick-start/js-precondition",
      "javascript/quick-start/js-token",
      "javascript/quick-start/js-room",
      "javascript/quick-start/js-player"
    ],
    "Initialization": [
      "javascript/parameters/js-sdk",
      "javascript/parameters/js-room",
      "javascript/parameters/js-player"
    ],
    "Features": [
      "javascript/features/js-tools",
      "javascript/features/js-view",
      "javascript/features/js-scenes",
      "javascript/features/js-state",
      "javascript/features/js-operation",
      "javascript/features/js-events",
      "javascript/features/js-plugin",
      "javascript/features/js-cursor",
      "javascript/features/js-document",
      "javascript/features/js-replay"
    ],
    "Upgrade": [
      "javascript/guide/js-v2migration"
    ]
  },
  "blog": {
    "Blog": [
      "blog/blog-glossary",
      "blog/blog-broadcast",
      "blog/blog-add-driver",
      "blog/debug-center",
      "blog/blog-begin-netless"
    ]
  },
  "server": {
    "Overview": [
      "server/overview/server-introduction"
    ],
    "Server API": [
      "server/api/server-request",
      "server/api/server-whiteboard-base",
      "server/api/server-whiteboard-cover",
      "server/api/server-whiteboard-scenes",
      "server/api/server-static-conversion",
      "server/api/server-dynamic-conversion",
      "server/api/server-postman-config"
    ]
  }
}
